walrus.py
walrus_compiler-0.0.0.dev0.dist-info/LICENSE
walrus_compiler-0.0.0.dev0.dist-info/METADATA
walrus_compiler-0.0.0.dev0.dist-info/WHEEL
walrus_compiler-0.0.0.dev0.dist-info/entry_points.txt
walrus_compiler-0.0.0.dev0.dist-info/top_level.txt
walrus_compiler-0.0.0.dev0.dist-info/zip-safe
walrus_compiler-0.0.0.dev0.dist-info/RECORD
